<annotation>
	<folder>train</folder>
	<filename>frame89.jpg</filename>
	<path>C:\Users\kappaavr\Desktop\gundetector\5 21st july\guns\train\frame89.jpg</path>
	<source>
		<database>Unknown</database>
	</source>
	<size>
		<width>600</width>
		<height>255</height>
		<depth>3</depth>
	</size>
	<segmented>0</segmented>
	<object>
		<name>gun</name>
		<pose>Unspecified</pose>
		<truncated>0</truncated>
		<difficult>0</difficult>
		<bndbox>
			<xmin>23</xmin>
			<ymin>4</ymin>
			<xmax>83</xmax>
			<ymax>42</ymax>
		</bndbox>
	</object>
	<object>
		<name>gun</name>
		<pose>Unspecified</pose>
		<truncated>0</truncated>
		<difficult>0</difficult>
		<bndbox>
			<xmin>198</xmin>
			<ymin>14</ymin>
			<xmax>260</xmax>
			<ymax>62</ymax>
		</bndbox>
	</object>
</annotation>
