<annotation>
	<folder>handgun</folder>
	<filename>image5.bmp</filename>
	<path>C:\Users\kappaavr\Desktop\gundetector\downloads\handguns\handgun\image5.bmp</path>
	<source>
		<database>Unknown</database>
	</source>
	<size>
		<width>0</width>
		<height>0</height>
		<depth>3</depth>
	</size>
	<segmented>0</segmented>
	<object>
		<name>gun</name>
		<pose>Unspecified</pose>
		<truncated>0</truncated>
		<difficult>0</difficult>
		<bndbox>
			<xmin>1712</xmin>
			<ymin>791</ymin>
			<xmax>3357</xmax>
			<ymax>1791</ymax>
		</bndbox>
	</object>
	<object>
		<name>gun</name>
		<pose>Unspecified</pose>
		<truncated>0</truncated>
		<difficult>0</difficult>
		<bndbox>
			<xmin>129</xmin>
			<ymin>360</ymin>
			<xmax>1757</xmax>
			<ymax>1515</ymax>
		</bndbox>
	</object>
</annotation>
